locomotive/README.md
locomotive/__init__.py
locomotive/api/__init__.py
locomotive/api/client.py
locomotive/api/gc.py
locomotive/api/oui_v3.py
locomotive/api/requests.py
locomotive/cli/__init__.py
locomotive/cli/commands/__init__.py
locomotive/cli/commands/live.py
locomotive/cli/commands/search.py
locomotive/cli/ext.py
locomotive/cli/formatters.py
locomotive/cli/templates/__init__.py
locomotive/cli/templates/journey.txt
locomotive/data/__init__.py
locomotive/data/stations.sqlite3
locomotive/diff.py
locomotive/exceptions.py
locomotive/models/__init__.py
locomotive/models/board.py
locomotive/models/journey.py
locomotive/models/passenger.py
locomotive/models/station.py
locomotive/normalization.py
locomotive/py.typed
locomotive/stores.py
locomotive-0.9.3.dist-info/entry_points.txt
locomotive-0.9.3.dist-info/LICENSE
locomotive-0.9.3.dist-info/WHEEL
locomotive-0.9.3.dist-info/METADATA
locomotive-0.9.3.dist-info/RECORD
