Metadata-Version: 2.1
Name: locomotive
Version: 0.9.3
Summary: Python API clients and a CLI for France's railways.
Home-page: https://github.com/maxmouchet/locomotive
License: MIT
Keywords: api,cli,sncf,train,france,tgv,ter
Author: Yann Feunteun, Maxime Mouchet
Requires-Python: >=3.6,<4.0
Classifier: Environment :: Console
Classifier: License :: OSI Approved :: MIT License
Classifier: Operating System :: OS Independent
Classifier: Programming Language :: Python :: 3
Classifier: Programming Language :: Python :: 3.6
Classifier: Programming Language :: Python :: 3.7
Classifier: Programming Language :: Python :: 3.8
Classifier: Typing :: Typed
Requires-Dist: attrs (>=19.3,<20.0)
Requires-Dist: click (>=7.0,<8.0)
Requires-Dist: colored (>=1.4.2,<2.0.0)
Requires-Dist: dateparser (>=0.7,<0.8)
Requires-Dist: faker (>=3.0.0,<4.0.0)
Requires-Dist: geopy (>=1.20,<2.0)
Requires-Dist: jinja2 (>=2.11.1,<3.0.0)
Requires-Dist: pendulum (>=2.0.5,<3.0.0)
Requires-Dist: py-money (>=0.4.0,<0.5.0)
Requires-Dist: requests (>=2.20,<3.0)
Requires-Dist: tableformatter (>=0.1.4,<0.2.0)
Requires-Dist: text-unidecode (>=1.3,<2.0)
Requires-Dist: tqdm (>=4.42.1,<5.0.0)
Project-URL: Documentation, https://maxmouchet.github.io/locomotive/
Project-URL: Repository, https://github.com/maxmouchet/locomotive
